{
  "node_id": "1135",
  "title": "كيفية الوضوء",
  "idfrom": 1135,
  "idto": 1135,
  "paragraphs": [
    {
      "kind": "text",
      "text": "ثُمَّ"
    },
    {
      "kind": "text",
      "text": "عِنْدَ الْفَرَاغِ مِنَ السِّوَاكِ يَجْلِسُ"
    },
    {
      "kind": "heading",
      "text": "وَيَقُولُ : بِسْمِ اللَّهِ الرَّحْمَنِ الرَّحِيمِ قَالَ صَلَّى اللَّهُ عَلَيْهِ وَسَلَّمَ :"
    },
    {
      "kind": "hadith",
      "text": "(( لَا وُضُوءَ لِمَنْ لَمْ يُسَمِّ اللَّهَ تَعَالَى ))"
    },
    {
      "kind": "text",
      "text": "أَيْ لَا وُضُوءَ كَامِلًا ."
    }
  ],
  "has_quran": false,
  "has_hadith": true,
  "level": 4
}