{
  "node_id": "1382",
  "title": "قسم 1382",
  "level": 1,
  "idfrom": 1382,
  "idto": 1382,
  "paragraphs": [
    {
      "kind": "break",
      "text": "[SECTION_BREAK]"
    },
    {
      "kind": "heading",
      "text": "وَقَالَ صَلَّى اللَّهُ عَلَيْهِ وَسَلَّمَ :"
    },
    {
      "kind": "hadith",
      "text": "(( مَنْ أَلِفَ الْمَسْجِدَ أَلِفَهُ اللَّهُ تَعَالَى ))"
    },
    {
      "kind": "hadith",
      "text": "(( إِذَا دَخَلَ أَحَدُكُمُ الْمَسْجِدَ فَلْيَرْكَعْ رَكْعَتَيْنِ قَبْلَ أَنْ يَجْلِسَ ))"
    },
    {
      "kind": "break",
      "text": "[SECTION_BREAK]"
    }
  ],
  "has_quran": false,
  "has_hadith": true
}