{
  "node_id": "3431",
  "title": "قسم 3431",
  "idfrom": 3431,
  "idto": 3431,
  "paragraphs": [
    {
      "kind": "text",
      "text": "وَأَمَّا"
    },
    {
      "kind": "text",
      "text": "رَمْيُ الْجِمَارِ فَاقْصِدْ بِهِ الِانْقِيَادَ لِلْأَمْرِ إِظْهَارًا لِلرِّقِّ وَالْعُبُودِيَّةِ"
    },
    {
      "kind": "text",
      "text": "وَانْتِهَاضًا لِمُجَرَّدِ الِامْتِثَالِ مِنْ غَيْرِ حَظٍّ لِلْعَقْلِ وَالنَّفْسِ فِيهِ ثُمَّ اقْصِدْ بِهِ التَّشَبُّهَ"
    },
    {
      "kind": "text",
      "text": "(بِإِبْرَاهِيمَ)"
    },
    {
      "kind": "text",
      "text": "عَلَيْهِ السَّلَامُ حَيْثُ عَرَضَ لَهُ إِبْلِيسُ لَعَنَهُ اللَّهُ تَعَالَى فِي ذَلِكَ الْمَوْضِعِ لِيُدْخِلَ عَلَى حَجِّهِ شُبْهَةً ، أَوْ يَفْتِنَهُ بِمَعْصِيَةٍ فَأَمَرَهُ اللَّهُ عَزَّ وَجَلَّ أَنْ يَرْمِيَهُ بِالْحِجَارَةِ طَرْدًا لَهُ وَقَطْعًا لِأَمَلِهِ ."
    },
    {
      "kind": "text",
      "text": "فَإِنْ خَطَرَ لَكَ أَنَّ الشَّيْطَانَ عَرَضَ لَهُ ، وَشَاهَدَهُ فَلِذَلِكَ رَمَاهُ ، وَأَمَّا أَنَا فَلَيْسَ يَعْرِضُ لِي الشَّيْطَانُ ، فَاعْلَمْ أَنَّ هَذَا الْخَاطِرَ مِنَ الشَّيْطَانِ ، وَأَنَّهُ الَّذِي أَلْقَاهُ فِي قَلْبِكَ لِيُفَتِّرَ عَزْمَكَ فِي الرَّمْيِ وَيُخَيِّلَ إِلَيْكَ أَنَّهُ فِعْلٌ لَا فَائِدَةَ فِيهِ ، وَأَنَّهُ يُضَاهِي اللَّعِبَ فَلَمْ تَشْتَغِلْ بِهِ فَاطْرُدْهُ عَنْ نَفْسِكَ بِالْجِدِّ وَالتَّشْمِيرِ فِي الرَّمْيِ فِيهِ بِرَغْمِ ، أَنْفَ الشَّيْطَانِ ."
    },
    {
      "kind": "text",
      "text": "وَاعْلَمْ أَنَّكَ فِي الظَّاهِرِ تَرْمِي الْحَصَى إِلَى الْعَقَبَةِ ، وَفِي الْحَقِيقَةِ تَرْمِي بِهِ وَجْهَ الشَّيْطَانِ وَتَقْصِمُ بِهِ ظَهْرَهُ إِذْ لَا يَحْصُلُ إِرْغَامُ أَنْفِهِ إِلَّا بِامْتِثَالِكَ أَمْرَ اللَّهِ سُبْحَانَهُ وَتَعَالَى تَعْظِيمًا لَهُ بِمُجَرَّدِ الْأَمْرِ مِنْ غَيْرِ حَظِّ لِلنَّفْسِ ، وَالْعَقْلِ فِيهِ ."
    }
  ],
  "has_quran": false,
  "has_hadith": false
}