{
  "node_id": "4154",
  "title": "قسم 4154",
  "idfrom": 4154,
  "idto": 4154,
  "paragraphs": [
    {
      "kind": "heading",
      "text": "الْخَامِسُ :"
    },
    {
      "kind": "text",
      "text": "الْحِمْيَةُ"
    },
    {
      "kind": "text",
      "text": "تَضُرُّ بِالصَّحِيحِ كَمَا يَضُرُّ تَرْكُهَا بِالْمَرِيضِ هَكَذَا قِيلَ ."
    },
    {
      "kind": "text",
      "text": "وَقَالَ بَعْضُهُمْ : مَنِ احْتَمَى فَهُوَ عَلَى يَقِينٍ مِنَ الْمَكْرُوهِ وَعَلَى شَكٍّ مِنَ الْعُوَافِي وَهَذَا حَسَنٌ فِي حَالِ الصِّحَّةِ وَرَأَى رَسُولُ اللَّهِ صَلَّى اللَّهُ عَلَيْهِ وَسَلَّمَ صُهَيْبًا يَأْكُلُ تَمْرًا وَإِحْدَى عَيْنَيْهِ رَمْدَاءُ فَقَالَ ."
    },
    {
      "kind": "text",
      "text": "أَتَأْكُلُ التَّمْرَ وَأَنْتَ رَمِدٌ ؟ فَقَالَ : يَا رَسُولَ اللَّهِ ، إِنَّمَا آكُلُ بِالشِّقِّ الْآخَرِ ."
    },
    {
      "kind": "text",
      "text": "يَعْنِي جَانِبَ السَّلِيمَةِ ، فَضَحِكَ رَسُولُ اللَّهِ صَلَّى اللَّهُ عَلَيْهِ وَسَلَّمَ ."
    }
  ],
  "has_quran": false,
  "has_hadith": false
}