{
  "node_id": "4379",
  "title": "قسم 4379",
  "idfrom": 4379,
  "idto": 4379,
  "paragraphs": [
    {
      "kind": "heading",
      "text": "وَيُكْرَهُ لَهُ الْجِمَاعُ فِي ثَلَاثِ لَيَالٍ مِنَ الشَّهْرِ :"
    },
    {
      "kind": "text",
      "text": "الْأَوَّلِ ، وَالْآخِرِ ، وَالنِّصْفِ ."
    },
    {
      "kind": "text",
      "text": "يُقَالُ : إِنَّ الشَّيْطَانَ يَحْضُرُ الْجِمَاعَ فِي هَذِهِ اللَّيَالِيَ ، وَيُقَالُ : إِنَّ الشَّيَاطِينَ يُجَامِعُونَ فِيهَا وَرُوِيَ كَرَاهَةُ ، ذَلِكَ : عَنْ"
    },
    {
      "kind": "text",
      "text": "عَلِيٍّ ،"
    },
    {
      "kind": "text",
      "text": "وَمُعَاوِيَةَ ،"
    },
    {
      "kind": "text",
      "text": "وَأَبِي هُرَيْرَةَ ،"
    },
    {
      "kind": "text",
      "text": "رَضِيَ اللَّهُ عَنْهُمْ ."
    },
    {
      "kind": "text",
      "text": "وَمِنَ الْعُلَمَاءِ مَنِ اسْتَحَبَّ"
    },
    {
      "kind": "text",
      "text": "الْجِمَاعَ يَوْمَ الْجُمُعَةِ وَلَيْلَتَهُ ،"
    },
    {
      "kind": "heading",
      "text": "تَحْقِيقًا لِأَحَدِ التَّأْوِيلَيْنِ ، مِنْ قَوْلِهِ صَلَّى اللَّهُ عَلَيْهِ وَسَلَّمَ :"
    },
    {
      "kind": "hadith",
      "text": "(( رَحِمَ اللَّهُ مَنْ غَسَّلَ وَاغْتَسَلَ .. الْحَدِيثَ .... ))"
    },
    {
      "kind": "text",
      "text": "ثُمَّ إِذَا قَضَى وَطَرَهُ فَلْيَتَمَهَّلْ عَلَى أَهْلِهِ حَتَّى تَقْضِيَ هِيَ أَيْضًا نَهْمَتَهَا فَإِنَّ إِنْزَالَهَا رُبَّمَا يَتَأَخَّرُ فَيُهَيِّجُ شَهْوَتَهَا ، ثُمَّ الْقُعُودُ عَنْهَا إِيذَاءٌ لَهَا وَالِاخْتِلَافُ فِي طَبْعِ الْإِنْزَالِ يُوجِبُ التَّنَافُرَ مَهْمَا كَانَ الزَّوْجُ سَابِقًا إِلَى الْإِنْزَالِ وَالتَّوَافُقُ فِي وَقْتِ الْإِنْزَالِ أَلَذُّ عِنْدِهَا لِيَشْتَغِلَ الرَّجُلُ بِنَفْسِهِ عَنْهَا ، فَإِنَّهَا رُبَّمَا تَسْتَحِي ."
    }
  ],
  "has_quran": false,
  "has_hadith": true
}