{
  "node_id": "4687",
  "title": "القسم الأول الحرام لصفة في عينه",
  "level": 5,
  "idfrom": 4687,
  "idto": 4687,
  "paragraphs": [
    {
      "kind": "break",
      "text": ""
    },
    {
      "kind": "text",
      "text": "وَأَمَّا الْحَيَوَانَاتُ فَتَنْقَسِمُ إِلَى مَا يُؤْكَلُ وَإِلَى مَا لَا يُؤْكَلُ ، وَتَفْصِيلُهُ فِي كِتَابِ الْأَطْعِمَةِ وَالنَّظَرُ يَطُولُ فِي تَفْصِيلِهِ لَا سِيَّمَا فِي الطُّيُورِ الْغَرِيبَةِ وَحَيَوَانَاتِ الْبَرِّ وَالْبَحْرِ وَمَا يَحِلُّ أَكْلُهُ مِنْهَا فَإِنَّمَا يَحِلُّ إِذَا ذُبِحَ ذَبْحًا شَرْعِيًّا رُوعِيَ ، فِيهِ شُرُوطُ الذَّابِحِ وَالْآلَةِ وَالذَّبْحِ وَذَلِكَ مَذْكُورٌ فِي كِتَابِ الصَّيْدِ وَالذَّبَائِحِ"
    },
    {
      "kind": "text",
      "text": "وَمَا لَمْ يُذْبَحْ ذَبْحًا شَرْعِيًّا أَوْ مَاتَ فَهُوَ حَرَامٌ وَلَا يَحِلُّ إِلَّا مِيتَتَانِ ; السَّمَكُ وَالْجَرَادُ"
    },
    {
      "kind": "break",
      "text": ""
    }
  ],
  "has_quran": false,
  "has_hadith": false
}