{
  "node_id": "4965",
  "title": "قسم 4965",
  "idfrom": 4965,
  "idto": 4965,
  "paragraphs": [
    {
      "kind": "text",
      "text": "وَدَخَلَ"
    },
    {
      "kind": "text",
      "text": "(ابْنُ أَبِي شُمَيْلَةَ)"
    },
    {
      "kind": "text",
      "text": "عَلَى"
    },
    {
      "kind": "text",
      "text": "عَبْدِ الْمَلِكِ بْنِ مَرْوَانَ"
    },
    {
      "kind": "text",
      "text": "فَقَالَ لَهُ : تَكَلَّمْ ، فَقَالَ لَهُ : إِنَّ النَّاسَ لَا يَنْجُونَ فِي الْقِيَامَةِ مِنْ غُصَصِهَا وَمِرَارَاتِهَا وَمُعَايَنَةِ الرَّدَى فِيهَا إِلَّا مَنْ أَرْضَى اللَّهَ بِسَخَطِ نَفْسِهِ ، فَبَكَى"
    },
    {
      "kind": "text",
      "text": "(عَبْدُ الْمَلِكِ)"
    },
    {
      "kind": "text",
      "text": "وَقَالَ لَأَجْعَلَنَّ هَذِهِ الْكَلِمَةَ مِثَالًا نُصْبَ عَيْنَيَّ مَا عِشْتُ ."
    },
    {
      "kind": "text",
      "text": "وَلَمَّا اسْتَعْمَلَ"
    },
    {
      "kind": "text",
      "text": "عُثْمَانُ بْنُ عَفَّانَ"
    },
    {
      "kind": "text",
      "text": "رَضِيَ اللَّهُ عَنْهُ"
    },
    {
      "kind": "text",
      "text": "(عَبْدَ اللَّهَ بْنَ عَامِرٍ)"
    },
    {
      "kind": "text",
      "text": "أَتَاهُ أَصْحَابُ رَسُولِ اللَّهِ صَلَّى اللَّهُ عَلَيْهِ وَسَلَّمَ وَأَبْطَأَ عَنْهُ"
    },
    {
      "kind": "text",
      "text": "أَبُو ذَرٍّ"
    },
    {
      "kind": "text",
      "text": "وَكَانَ لَهُ صَدِيقًا فَعَاتَبَهُ فَقَالَ"
    },
    {
      "kind": "heading",
      "text": ": سَمِعْتُ رَسُولَ اللَّهِ صَلَّى اللَّهُ عَلَيْهِ وَسَلَّمَ يَقُولُ إِنَّ :"
    },
    {
      "kind": "hadith",
      "text": "(( الرَّجُلَ إِذَا وَلَّى وِلَايَتَهُ تَبَاعَدَ اللَّهُ عَنْهُ ))"
    },
    {
      "kind": "text",
      "text": "وَدَخَلَ مَالِكُ بْنُ دِينَارٍ عَلَى أَمِيرِ"
    },
    {
      "kind": "text",
      "text": "(الْبَصْرَةِ)"
    },
    {
      "kind": "text",
      "text": "فَقَالَ : أَيُّهَا الْأَمِيرُ ، قَرَأْتُ فِي بَعْضِ الْكُتُبِ إِنَّ اللَّهَ تَعَالَى يَقُولُ؛ مَا أَحْمَقَ مِنْ سُلْطَانٍ وَمَا أَجْهَلَ مِمَّنْ عَصَانِي وَمَنْ أَعَزُّ مِمَّنِ اعْتَزَّ بِي أَيُّهَا الرَّاعِي السُّوءُ دَفَعْتُ إِلَيْكَ غَنَمًا سِمَانًا صِحَاحًا ، فَأَكَلْتَ اللَّحْمَ وَلَبِسْتَ الصُّوفَ وَتَرَكْتَهَا عِظَامًا تَتَقَعْقَعُ فَقَالَ لَهُ وَالِي"
    },
    {
      "kind": "text",
      "text": "أَنَدْرِي : مَا الَّذِي يُجَرِّئُكَ عَلَيْنَا وَيُجَنِّبُنَا عَنْكَ ، قَالَ : لَا ، قَالَ : قِلَّةُ الطَّمَعِ فِينَا وَتَرْكُ الْإِمْسَاكِ لِمَا فِي أَيْدِينَا ."
    },
    {
      "kind": "text",
      "text": "وَكَانَ"
    },
    {
      "kind": "text",
      "text": "عُمَرُ بْنُ عَبْدِ الْعَزِيزِ"
    },
    {
      "kind": "text",
      "text": "وَاقِفًا مَعَ"
    },
    {
      "kind": "text",
      "text": "(سُلَيْمَانَ ابْنِ عَبْدِ الْمَلِكِ)"
    },
    {
      "kind": "text",
      "text": "فَسَمِعَ سُلَيْمَانُ صَوْتَ الرَّعْدِ فَجَزِعَ وَوَضَعَ صَدْرَهُ عَلَى مُقَدِّمَةِ الرَّحْلِ فَقَالَ لَهُ"
    },
    {
      "kind": "text",
      "text": "عُمَرُ"
    },
    {
      "kind": "text",
      "text": ": هَذَا صَوْتُ رَحْمَتِهِ فَكَيْفَ إِذَا سَمِعْتَ صَوْتَ عَذَابِهِ ، ثُمَّ نَظَرَ"
    },
    {
      "kind": "text",
      "text": "(سُلَيْمَانُ)"
    },
    {
      "kind": "text",
      "text": "إِلَى النَّاسِ فَقَالَ : مَا أَكْثَرَ النَّاسَ ، فَقَالَ"
    },
    {
      "kind": "text",
      "text": ": خُصَمَاؤُكَ يَا أَمِيرَ الْمُؤْمِنِينَ ، فَقَالَ لَهُ"
    },
    {
      "kind": "text",
      "text": ": ابْتَلَاكَ اللَّهُ بِهِمْ ."
    },
    {
      "kind": "text",
      "text": "وَحُكِيَ أَنَّ سُلَيْمَانَ بْنَ عَبْدِ الْمَلِكِ قَدِمَ"
    },
    {
      "kind": "text",
      "text": "(الْمَدِينَةَ)"
    },
    {
      "kind": "text",
      "text": "وَهُوَ يُرِيدُ"
    },
    {
      "kind": "text",
      "text": "(مَكَّةَ)"
    },
    {
      "kind": "text",
      "text": "، فَأَرْسَلَ إِلَى أَبِي حَازِمٍ فَدَعَاهُ فَلَمَّا دَخَلَ عَلَيْهِ قَالَ لَهُ"
    },
    {
      "kind": "text",
      "text": ": يَا"
    },
    {
      "kind": "text",
      "text": "(أَبَا حَازِمٍ)"
    },
    {
      "kind": "text",
      "text": "مَا لَنَا نَكْرَهُ الْمَوْتَ فَقَالَ : لِأَنَّكُمْ خَرَّبْتُمْ آخِرَتَكُمْ وَعَمَّرْتُمْ دُنْيَاكُمْ ، فَكَرِهْتُمْ أَنْ تَنْتَقِلُوا مِنَ الْعُمْرَانِ إِلَى الْخَرَابِ فَقَالَ : يَا"
    },
    {
      "kind": "text",
      "text": "كَيْفَ الْقُدُومُ عَلَى اللَّهِ قَالَ يَا أَمِيرَ الْمُؤْمِنِينَ ، أَمَّا الْمُحْسِنُ فَكَالْغَائِبِ يَقْدَمُ عَلَى أَهْلِهِ ، وَأَمَّا الْمُسِيءُ فَكَالْآبِقِ يُقْدَمُ عَلَى مَوْلَاهُ ، فَبَكَى"
    },
    {
      "kind": "text",
      "text": "وَقَالَ لَيْتَ شِعْرِي مَا لِي عِنْدَ اللَّهِ قَالَ"
    },
    {
      "kind": "text",
      "text": "(أَبُو حَازِمٍ)"
    },
    {
      "kind": "heading",
      "text": ": اعْرِضْ نَفْسَكَ عَلَى كِتَابِ اللَّهِ تَعَالَى حَيْثُ قَالَ :"
    },
    {
      "kind": "text",
      "text": "إِنَّ الأَبْرَارَ لَفِي نَعِيمٍ"
    },
    {
      "kind": "text",
      "text": "وَإِنَّ الْفُجَّارَ لَفِي جَحِيمٍ"
    },
    {
      "kind": "text",
      "text": "، قَالَ : فَأَيْنَ رَحْمَةُ اللَّهِ ؟ قَالَ قَرِيبٌ مِنَ الْمُحْسِنِينَ ثُمَّ ، قَالَ"
    },
    {
      "kind": "text",
      "text": "، أَيُّ عِبَادِ اللَّهِ أَكْرَمُ ؟ قَالَ : أَهْلُ الْبَرِّ وَالتَّقْوَى قَالَ : فَأَيُّ الْأَعْمَالِ أَفْضَلُ ، قَالَ : أَدَاءُ الْفَرَائِضِ مَعَ اجْتِنَابِ الْمَحَارِمِ قَالَ : فَأَيُّ الْكَلَامِ أَسْمَعُ ، قَالَ : قَوْلُ الْحَقِّ عِنْدَ مَنْ تَخَافُ وَتَرْجُو قَالَ فَأَيُّ الْمُؤْمِنِينَ أَكْيَسُ قَالَ : رَجُلٌ عَمِلَ بِطَاعَةِ اللَّهِ وَدَعَا النَّاسَ إِلَيْهَا قَالَ : فَأَيُّ الْمُؤْمِنِينَ أَخْسَرُ ؟ قَالَ رَجُلٌ خَطَا : فِي هَوَى أَخِيهِ ، وَهُوَ ظَالِمٌ ، فَبَاعَ آخِرَتَهُ بِدُنْيَا غَيْرِهِ قَالَ"
    },
    {
      "kind": "text",
      "text": "مَا تَقُولُ فِيمَا نَحْنُ فِيهِ ؟ قَالَ أَوَتَعْفِينِي؟ قَالَ: لَا بُدَّ فَإِنَّهَا نَصِيحَةٌ تُلْقِيهَا إِلَيَّ قَالَ : يَا أَمِيرَ الْمُؤْمِنِينَ إِنَّ : آبَاءَكَ قَهَرُوا النَّاسَ بِالسَّيْفِ وَأَخَذُوا هَذَا الْمُلْكَ عَنْوَةً مِنْ غَيْرِ مَشُورَةٍ مِنَ الْمُسْلِمِينَ وَلَا رِضًا مِنْهُمْ حَتَّى قَتَلُوا مِنْهُمْ مَقْتَلَةً عَظِيمَةً ، وَقَدِ ارْتَحَلُوا فَلَوْ شَعَرْتَ مِمَّا قَالُوا وَمَا قِيلَ لَهُمْ ، فَقَالَ لَهُ رَجُلٌ مِنْ جُلَسَائِهِ بِئْسَمَا قُلْتَ قَالَ"
    },
    {
      "kind": "text",
      "text": "إِنَّ اللَّهَ قَدْ أَخَذَ الْمِيثَاقَ عَلَى الْعُلَمَاءِ لِيُبَيِّنَنَّهُ لِلنَّاسِ وَلَا يَكْتُمُونَهُ ."
    },
    {
      "kind": "text",
      "text": "قَالَ وَكَيْفَ لَنَا أَنْ نُصْلِحَ هَذَا الْفَسَادَ ، قَالَ : أَنْ تَأْخُذَهُ مِنْ حَلِّهِ فَتَضَعَهُ فِي حَقِّهِ فَقَالَ"
    },
    {
      "kind": "text",
      "text": ": وَمَنْ يَقْدِرُ عَلَى ذَلِكَ فَقَالَ ؟ : مَنْ يَطْلُبُ الْجَنَّةَ وَيَخَافُ مِنْ النَّارَ ."
    },
    {
      "kind": "text",
      "text": "فَقَالَ"
    },
    {
      "kind": "text",
      "text": "ادْعُ لِي ."
    },
    {
      "kind": "heading",
      "text": "فَقَالَ :"
    },
    {
      "kind": "text",
      "text": "اللَّهُمَّ إِنْ كَانَ"
    },
    {
      "kind": "text",
      "text": "وَلِيَّكَ فَيَسِّرْهُ لِخَيْرَيِ الدُّنْيَا وَالْآخِرَةِ ، وَإِنْ كَانَ عَدُوَّكَ فَخُذْ بِنَاصِيَتِهِ إِلَى مَا تُحِبُّ وَتَرْضَى فَقَالَ سُلَيْمَانُ أَوْصِنِي ، فَقَالَ : أُوصِيكَ وَأُوجِزُ عَظِّمْ رَبَّكَ وَنَزِّهْهُ أَنْ يَرَاكَ حَيْثُ نَهَاكَ أَوْ يَفْقِدَكَ حَيْثُ أَمَرَكَ ."
    },
    {
      "kind": "text",
      "text": "وَقَالَ عُمَرُ بْنُ عَبْدِ الْعَزِيزِ لِأَبِي حَازِمٍ: عِظْنِي، فَقَالَ: اضْطَجِعْ ثُمَّ اجْعَلِ الْمَوْتَ عِنْدَ رَأْسِكَ ثُمَّ انْظُرْ إِلَى مَا تُحِبُّ أَنْ يَكُونَ فِيكَ تِلْكَ السَّاعَةَ فَخُذْ بِهِ الْآنَ وَمَا تَكْرَهُ أَنْ يَكُونَ فِيكَ تِلْكَ السَّاعَةَ فَدَعْهُ الْآنَ فَلَعَلَّ تِلْكَ السَّاعَةَ قَرِيبَةٌ ."
    },
    {
      "kind": "text",
      "text": "وَدَخَلَ أَعْرَابِيٌّ عَلَى"
    },
    {
      "kind": "text",
      "text": "سُلَيْمَانَ بْنِ عَبْدِ الْمَلِكِ"
    },
    {
      "kind": "text",
      "text": "فَقَالَ : تَكَلَّمْ يَا أَعْرَابِيُّ ، فَقَالَ : يَا أَمِيرَ الْمُؤْمِنِينَ إِنِّي مُكَلَّمُكَ بِكَلَامٍ فَاحْتَمِلْهُ وَإِنْ كَرِهْتَهُ ، فَإِنَّ وَرَاءَهُ مَا تُحِبُّ إِنْ قَبِلْتَهُ ، فَقَالَ : يَا أَعْرَابِيٌّ إِنَّا لَنَجُودُ بِسِعَةِ الِاحْتِمَالِ عَلَى مَنْ لَا نَرْجُو نُصْحَهُ وَلَا تَأْمَنُ غِشَّهُ فَكَيْفَ بِمَنْ نَأْمَنُ غِشَّهُ وَنَرْجُو نُصْحَهُ فَقَالَ الْأَعْرَابِيُّ : يَا أَمِيرَ الْمُؤْمِنِينَ إِنَّهُ قَدْ تَكَنَّفَكَ رِجَالٌ أَسَاءُوا الِاخْتِيَارَ لِأَنْفُسِهِمْ وَابْتَاعُوا دُنْيَاهُمْ بِدِينِهِمْ وَرِضَاكَ بِسَخَطِ رَبِّهِمْ خَافُوكَ فِي اللَّهِ تَعَالَى وَلَمْ يَخَافُوا اللَّهَ فِيكَ حَرْبُ الْآخِرَةِ ، سِلْمُ الدُّنْيَا ، فَلَا تَأْتَمِنْهُمْ عَلَى مَا ائْتَمَنَكَ اللَّهُ تَعَالَى عَلَيْهِ فَإِنَّهُمْ لَمْ يَأْلُوَا فِي الْأَمَانَةِ تَضْيِيعًا وَفِي الْأُمَّةِ خَسْفًا وَعَسْفًا وَأَنْتَ مَسْئُولٌ عَمَّا اجْتَرَحُوا ، وَلَيْسُوا بِمَسْئُولِينَ عَمَّا اجْتَرَحْتَ ، فَلَا تُصْلِحْ دُنْيَاهُمْ بِفَسَادِ آخِرَتِكَ ، فَإِنَّ أَعْظَمَ النَّاسِ غَبْنَا مَنْ بَاعَ آخِرَتَهُ بِدُنْيَا غَيْرِهِ فَقَالَ لَهُ"
    },
    {
      "kind": "text",
      "text": ": يَا أَعْرَابِيُّ أَمَا إِنَّكَ قَدْ سَلَلْتَ لِسَانَكَ وَهُوَ أَقْطَعُ سَيْفَيْكَ قَالَ : أَجَلْ يَا أَمِيرَ الْمُؤْمِنِينَ ، وَلَكِنْ لَكَ لَا عَلَيْكَ ."
    },
    {
      "kind": "text",
      "text": "وَحُكِيَ أَنَّ أَبَا بَكَرَةٍ دَخَلَ عَلَى مُعَاوِيَةَ فَقَالَ : اتَّقِ اللَّهَ يَا"
    },
    {
      "kind": "text",
      "text": "مُعَاوِيَةُ"
    },
    {
      "kind": "text",
      "text": "وَاعْلَمْ أَنَّكَ فِي كُلِّ يَوْمٍ يَخْرُجُ عَنْكَ ، وَفِي كُلِّ لَيْلَةٍ تَأْتِي عَلَيْكَ لَا تَزْدَادُ مِنَ الدُّنْيَا إِلَّا بُعْدًا ، وَمِنَ الْآخِرَةِ إِلَّا قُرْبًا وَعَلَى أَثَرِكَ طَالِبٌ لَا تَفُوتُهُ وَقَدْ نَصَبَ لَكَ عَلَمًا لَا تَجُوزُهُ فَمَا أَسْرَعَ مَا تَبْلُغُ الْعَلَمَ ، وَمَا أَوْشَكَ مَا يَلْحَقُ بِكَ الطَّالِبُ وَإِنَّا وَمَا نَحْنُ فِيهِ زَائِلٌ وَفِي الَّذِي نَحْنُ إِلَيْهِ صَائِرُونَ بَاقٍ إِنْ خَيْرًا فَخَيْرٌ ، وَإِنْ شَرًّا فَشَرٌّ ."
    },
    {
      "kind": "text",
      "text": "فَهَكَذَا كَانَ"
    },
    {
      "kind": "text",
      "text": "دُخُولُ أَهْلِ الْعِلْمِ"
    },
    {
      "kind": "text",
      "text": "أَعْنِي عُلَمَاءَ الْآخِرَةِ فَأَمَّا عُلَمَاءُ الدُّنْيَا فَيَدْخُلُونَ لِيَتَقَرَّبُوا إِلَى قُلُوبِهِمْ فَيَدُلُّونَهُمْ عَلَى الرُّخَصِ وَيَسْتَنْبِطُونَ لَهُمْ بِدَقَائِقِ الْحِيَلِ طُرُقَ السِّعَةِ فِيمَا يُوَافِقُ أَغْرَاضَهُمْ ."
    },
    {
      "kind": "text",
      "text": "وَإِنْ تَكَلَّمُوا بِمِثْلِ مَا ذَكَرْنَاهُ فِي مَعْرَضِ الْوَعْظِ لَمْ يَكُنْ قَصْدُهُمُ الْإِصْلَاحَ بَلِ اكْتِسَابُ الْجَاهِ وَالْقَبُولُ عِنْدَهُمْ ."
    },
    {
      "kind": "text",
      "text": "وَفِي هَذَا غُرُورَانِ يَغْتَرَّ بِهِمْ الْحَمْقَى أَحَدُهُمَا أَنْ يَظْهَرَ أَنَّ قَصْدِي فِي الدُّخُولِ عَلَيْهِمْ إِصْلَاحُهُمْ بِالْوَعْظِ ."
    },
    {
      "kind": "text",
      "text": "وَرُبَّمَا يُلَبِّسُونَ عَلَى أَنْفُسِهِمْ بِذَلِكَ ، وَإِنَّمَا الْبَاعِثُ لَهُمْ شَهْوَةٌ خَفِيَّةٌ لِلشُّهْرَةِ وَتَحْصِيلِ الْمَعْرِفَةِ عِنْدَهُمْ وَعَلَامَةُ الصِّدْقِ فِي طَلَبِ الْإِصْلَاحِ أَنَّهُ لَوْ تَوَلَّى ذَلِكَ الْوَعْظَ غَيْرُهُ مِمَّنْ هُوَ مِنْ أَقْرَانِهِ فِي الْعِلْمِ ، وَوَقَعَ مَوْقِعَ الْقَبُولِ وَظَهَرَ بِهِ أَثَرُ ، الصَّلَاحِ فَيَنْبَغِي أَنْ يَفْرَحَ بِهِ ، وَيَشْكُرَ اللَّهَ تَعَالَى عَلَى كِفَايَتِهِ ، هَذَا الْمُهِمُّ كَمَنْ وَجَبَ عَلَيْهِ أَنْ يُعَالِجَ مَرِيضًا ضَائِعًا فَقَامَ بِمُعَاجَلَتِهِ غَيْرَهُ فَإِنَّهُ يَعْظُمُ بِهِ فَرَحُهُ ."
    },
    {
      "kind": "text",
      "text": "فَإِنْ كَانَ يُصَادِفُ فِي قَلْبِهِ تَرْجِيحًا لِكَلَامِهِ عَلَى كَلَامِ غَيْرِهِ ، فَهُوَ مَغْرُورٌ الثَّانِي"
    },
    {
      "kind": "text",
      "text": "أَنْ يَزْعُمَ أَنِّي أَقْصِدُ الشَّفَاعَةَ لِمُسْلِمٍ فِي دَفْعِ ظُلَامَةٍ"
    },
    {
      "kind": "text",
      "text": "وَهَذَا أَيْضًا مَظِنَّةُ الْغُرُورِ وَمِعْيَارُهُ مَا تَقَدَّمَ ذِكْرُهُ ."
    }
  ],
  "has_quran": false,
  "has_hadith": true
}