{
  "node_id": "521",
  "title": "معنى الكلمة الثانية من الشهادتين وهي الشهادة للرسول",
  "level": 4,
  "idfrom": 521,
  "idto": 521,
  "paragraphs": [
    {
      "kind": "break",
      "text": ""
    },
    {
      "kind": "text",
      "text": "فَنَسَخَ بِشَرِيعَتِهِ الشَّرَائِعَ"
    },
    {
      "kind": "text",
      "text": "إِلَّا مَا قَرَّرَهُ مِنْهَا"
    },
    {
      "kind": "text",
      "text": "وَفَضَّلَهُ عَلَى سَائِرِ الْأَنْبِيَاءِ"
    },
    {
      "kind": "break",
      "text": ""
    }
  ],
  "has_quran": false,
  "has_hadith": false
}