{
  "node_id": "6437",
  "title": "بيان حد النميمة وما يجب في ردها",
  "idfrom": 6437,
  "idto": 6437,
  "paragraphs": [
    {
      "kind": "text",
      "text": "بَيَانُ"
    },
    {
      "kind": "text",
      "text": "حَدِّ النَّمِيمَةِ وَمَا يَجِبُ فِي رَدِّهَا"
    },
    {
      "kind": "text",
      "text": "اعْلَمْ أَنَّ اسْمَ النَّمِيمَةِ إِنَّمَا يُطْلَقُ فِي الْأَكْثَرِ عَلَى مَنْ يَنِمُّ قَوْلَ الْغَيْرِ إِلَى الْمَقُولِ فِيهِ ، كَمَا تَقُولُ فُلَانٌ كَانَ يَتَكَلَّمُ فِيكَ بِكَذَا وَكَذَا وَلَيْسَتِ النَّمِيمَةُ مُخْتَصَّةً بِهِ ، بَلْ حَدُّهَا كَشْفُ مَا يُكْرَهُ كَشْفُهُ ، سَوَاءٌ كَرِهَهُ الْمَنْقُولُ عَنْهُ ، أَوِ الْمَنْقُولُ إِلَيْهِ ، أَوْ كَرِهَهُ ثَالِثٌ ، وَسَوَاءٌ كَانَ الْكَشْفُ بِالْقَوْلِ أَوْ بِالْكِتَابَةِ أَوْ بِالرَّمْزِ أَوْ بِالْإِيمَاءِ وَسَوَاءٌ كَانَ الْمَنْقُولُ مِنَ الْأَعْمَالِ ، أَوْ مِنَ الْأَقْوَالِ ، وَسَوَاءٌ كَانَ ذَلِكَ عَيْبًا وَنَقْصًا فِي الْمَنْقُولِ عَنْهُ ، أَوْ لَمْ يَكُنْ ، بَلْ حَقِيقَةُ النَّمِيمَةِ إِفْشَاءُ السِّرِّ وَهَتْكُ السِّتْرِ عَمَّا يَكْرَهُ كَشْفَهُ بَلْ كَانَ مَا رَآهُ الْإِنْسَانُ مِنْ أَحْوَالِ النَّاسِ مِمَّا يَكْرَهُ فَيَنْبَغِي أَنْ يَسْكُتَ عَنْهُ إِلَّا مَا فِي حِكَايَتِهِ فَائِدَةٌ لِمُسْلِمٍ أَوْ دَفْعٌ لِمَعْصِيَةٍ ، كَمَا إِذَا رَأَى مَنْ يَتَنَاوَلُ مَالَ غَيْرِهِ فَعَلَيْهِ أَنْ يَشْهَدَ بِهِ ؛ مُرَاعَاةً لِحَقِّ الْمَشْهُودِ لَهُ ، فَأَمَّا إِذَا رَآهُ يُخْفِي مَالًا لِنَفَسِهِ فَذِكْرُهُ فَهُوَ نَمِيمَةٌ وَإِفْشَاءٌ لِلسِّرِّ ، فَإِنْ كَانَ مَا يُنِمُّ بِهِ نَقْصًا وَعَيْبًا فِي الْمَحْكِيِّ عَنْهُ ، كَانَ قَدْ"
    },
    {
      "kind": "text",
      "text": "جَمَعَ بَيْنَ الْغِيبَةِ وَالنَّمِيمَةِ"
    },
    {
      "kind": "text",
      "text": "فَالْبَاعِثُ عَلَى النَّمِيمَةِ"
    },
    {
      "kind": "text",
      "text": "إِمَّا إِرَادَةُ السُّوءِ لِلْمَحْكِيِّ عَنْهُ أَوْ إِظْهَارُ الْحُبِّ لِلْمَحْكِيِّ لَهُ أَوِ التَّفَرُّجُ بِالْحَدِيثِ وَالْخَوْضِ فِي الْفُضُولِ وَالْبَاطِلِ ."
    },
    {
      "kind": "text",
      "text": "وَكُلُّ مَنْ حُمِلَتْ إِلَيْهِ النَّمِيمَةُ ، وَقِيلَ لَهُ : إِنَّ فُلَانًا قَالَ فِيكَ كَذَا وَكَذَا ، أَوْ فَعَلَ فِي حَقِّكَ كَذَا ، أَوْ هُوَ يُدَبِّرُ فِي إِفْسَادِ أَمْرِكَ ، أَوْ فِي مُمَالَأَةِ عَدُوِّكَ أَوْ تَقْبِيحِ حَالِكَ ، أَوْ مَا يَجْرِي مُجْرَاهُ ، فَعَلَيْهِ سِتَّةُ أُمُورٍ : الْأَوَّلُ أَنْ لَا يُصَدِّقَهُ لِأَنَّ النَّمَّامَ فَاسِقٌ وَهُوَ مَرْدُودُ الشَّهَادَةِ قَالَ اللَّهُ تَعَالَى"
    },
    {
      "kind": "text",
      "text": "يَا أَيُّهَا الَّذِينَ آمَنُوا إِنْ جَاءَكُمْ فَاسِقٌ بِنَبَإٍ فَتَبَيَّنُوا أَنْ تُصِيبُوا قَوْمًا بِجَهَالَةٍ"
    },
    {
      "kind": "text",
      "text": "الثَّانِي : أَنْ يَنْهَاهُ عَنْ ذَلِكَ وَيَنْصَحَ لَهُ وَيُقَبِّحَ عَلَيْهِ فِعْلَهُ قَالَ اللَّهُ تَعَالَى :"
    },
    {
      "kind": "text",
      "text": "وَأْمُرْ بِالْمَعْرُوفِ وَانْهَ عَنِ الْمُنْكَرِ"
    },
    {
      "kind": "text",
      "text": "الثَّالِثُ أَنْ يُبْغِضَهُ فِي اللَّهِ تَعَالَى ، فَإِنَّهُ بَغِيضٌ عِنْدَ اللَّهِ تَعَالَى وَيَجِبُ بُغْضُ مَنْ يُبْغِضُهُ اللَّهُ تَعَالَى ."
    },
    {
      "kind": "heading",
      "text": "الرَّابِعُ أَنْ لَا . تَظُنَّ بِأَخِيكَ الْغَائِبِ السُّوءَ لِقَوْلِ اللَّهِ ؛ تَعَالَى :"
    },
    {
      "kind": "text",
      "text": "اجْتَنِبُوا كَثِيرًا مِنَ الظَّنِّ إِنَّ بَعْضَ الظَّنِّ إِثْمٌ"
    },
    {
      "kind": "text",
      "text": "الْخَامِسُ أَنْ لَا : يَحْمِلَكَ مَا حَكَى لَكَ عَلَى التَّجَسُّسِ وَالْبَحْثِ لِتُحَقِّقَ اتِّبَاعًا لِقَوْلِ اللَّهِ تَعَالَى :"
    },
    {
      "kind": "text",
      "text": "وَلا تَجَسَّسُوا"
    },
    {
      "kind": "text",
      "text": "السَّادِسُ أَنْ لَا : تَرْضَى لِنَفْسِكَ مَا نَهَيْتَ النَّمَّامَ عَنْهُ وَلَا ، تَحْكِيَ نَمِيمَتَهُ فَتَقُولَ : فُلَانٌ قَدْ حَكَى لِي كَذَا وَكَذَا ، فَتَكُونَ بِهِ نَمَّامًا وَمُغْتَابًا وَقَدْ تَكُونُ قَدْ أَتَيْتَ مَا عَنْهُ نُهِيتَ وَقَدْ رُوِيَ عَنْ"
    },
    {
      "kind": "text",
      "text": "عُمَرَ بْنِ عَبْدِ الْعَزِيزِ"
    },
    {
      "kind": "text",
      "text": "رَضِيَ اللَّهُ عَنْهُ أَنَّهُ دَخَلَ عَلَيْهِ رَجُلٌ فَذَكَرَ لَهُ عَنْ رَجُلٍ شَيْئًا ، فَقَالَ لَهُ"
    },
    {
      "kind": "text",
      "text": "عُمَرُ"
    },
    {
      "kind": "heading",
      "text": ": إِنْ شِئْتَ نَظَرْنَا فِي أَمْرِكَ فَإِنْ كُنْتَ كَاذِبًا فَأَنْتَ مِنْ أَهْلِ هَذِهِ الْآيَةِ :"
    },
    {
      "kind": "text",
      "text": "إِنْ جَاءَكُمْ فَاسِقٌ بِنَبَإٍ فَتَبَيَّنُوا"
    },
    {
      "kind": "heading",
      "text": "، وَإِنْ كُنْتَ صَادِقًا فَأَنْتَ مِنْ أَهْلِ هَذِهِ الْآيَةِ :"
    },
    {
      "kind": "text",
      "text": "هَمَّازٍ مَشَّاءٍ بِنَمِيمٍ"
    },
    {
      "kind": "text",
      "text": "، وَإِنْ شِئْتَ عَفَوْنَا عَنْكَ . فَقَالَ : الْعَفْوَ يَا أَمِيرَ الْمُؤْمِنِينَ ، لَا أَعُودُ إِلَيْهِ أَبَدًا ."
    }
  ],
  "has_quran": false,
  "has_hadith": false,
  "level": 3
}