{
  "node_id": "7396",
  "title": "قسم 7396",
  "level": 1,
  "idfrom": 7396,
  "idto": 7396,
  "paragraphs": [
    {
      "kind": "break",
      "text": "[SECTION_BREAK]"
    },
    {
      "kind": "heading",
      "text": "وَقِيلَ :"
    },
    {
      "kind": "text",
      "text": "الصَّبْرُ لِلَّهِ غَنَاءٌ وَالصَّبْرُ بِاللَّهِ بَقَاءٌ وَالصَّبْرُ مَعَ اللَّهِ وَفَاءٌ وَالصَّبْرُ عَنِ اللَّهِ جَفَاءٌ"
    },
    {
      "kind": "text",
      "text": "وَقَدْ قِيلَ فِي مَعْنَاهُ ."
    },
    {
      "kind": "center",
      "text": "[CENTER]وَالصَّبْرُ عَنْكَ فَمَذْمُومٌ عَوَاقِبُهُ وَالصَّبْرُ فِي سَائِرِ الْأَشْيَاءِ مَحْمُودُ[/CENTER]"
    },
    {
      "kind": "heading",
      "text": "وَقِيلَ أَيْضًا :"
    },
    {
      "kind": "center",
      "text": "[CENTER]الصَّبْرُ يُحْمَلُ فِي الْمَوَاطِنِ كُلِّهَا     إِلَّا عَلَيْكَ فَإِنَّهُ لَا يُجْمَلُ[/CENTER]"
    },
    {
      "kind": "text",
      "text": "هَذَا آخِرُ مَا أَرَدْنَا شَرْحَهُ عَنْ عُلُومِ الصَّبْرِ وَأَسْرَارِهِ ."
    },
    {
      "kind": "break",
      "text": "[SECTION_BREAK]"
    }
  ],
  "has_quran": false,
  "has_hadith": false
}